{
    "method": "random",
    "metric": {"goal": "minimize", "name": "test_loss"},
    "parameters": {
        "epochs": {"values": [-1]},
        "batch_size": {"values": [8, 32, 128]},
        "lr": {"values": [0.1, 0.01, 0.001]},
        "learning_rule": {"values": ["softhebb"]},
        "dataset": {"values": ["cifar10"]},
        "model_size": {"values": [128, 256, 512]},
        "model_depth": {"values": [2, 4, 8, 16]},
        "supervised": {"values": [true]},
        "task": {"values": ["classification"]},
        "model_type": {"values": ["mlp-1"]},
        "norm": {"values": ["batch", "layer"]},
        "adaptive_lr": {"values": [true, false]},
        "adaptive_lr_power": {"min": 0.1, "max": 1.0, "distribution": "uniform"},
        "lr_schedule": {"values": ["constant"]},
        "init": {"values": ["xavier", "positive-uniform", "normal"]},
        "R": {"min": 1.0, "max": 10.0, "distribution": "uniform"},
        "influence_type": {"values": ["grad", "simple"]},
        "dot_uw": {"values": [false]},
        "pooling": {"values": ["none", "max", "avg"]},
        "temp": {"values": [0.5, 1, 2, 4, 8, 16]},
        "name": {"values": [""]},
        "influencehebb_soft_y": {"values": [true]},
        "influencehebb_soft_z": {"values": [true]},
        "activation": {"values": ["relu"]}
    }
}